Workbook

Sheet Overview
B2: e-Rumah | Testing and Verification Checklist
B3: Centralized Reverse Mortgage Marketplace for Elderly Financial Support
B5: Student: | C5: Ho Kang Kai
B6: Institution: | C6: Faculty of Computing and Information Technology, TAR UMT, Kuala Lumpur
B7: Academic Year: | C7: 2025/26
B8: Repository: | C8: github.com/Kangkai64/e-Rumah
B9: Requirement source: | C9: FYP Report Chapter 4 functional (FR) and non-functional (NFR) requirements
B11: How to use
B12: 1. Each module has its own sheet. Every row is one test item mapped to a requirement ID from Chapter 4 where applicable.
B13: 2. Execute the Verification Steps, compare against the Expected Result, then set Status via the dropdown (Pass, Fail, Partial, Blocked, Not Tested).
B14: 3. Record evidence or deviations under Actual Result / Remarks and enter the Date Tested.
B15: 4. The supervisor marks the final column (Yes / No / N/A) after reviewing the demonstrated behaviour.
B16: 5. The summary table below updates automatically as statuses are filled in.
B18: Status legend
B19: Pass | C19: Behaves exactly as expected
B20: Fail | C20: Does not meet the expected result
B21: Partial | C21: Works with minor deviations noted in remarks
B22: Blocked | C22: Cannot be tested due to a dependency or environment issue
B23: Not Tested | C23: Not yet executed
B25: Module summary
B26: Module | C26: Total | D26: Pass | E26: Fail | F26: Partial | G26: Blocked | H26: Not Tested | I26: Tested % | J26: Supervisor Verified
B27: 1. Health Monitoring | C27: =COUNTA('1. Health Monitoring'!$A$5:$A$25) -> 21 | D27: =COUNTIF('1. Health Monitoring'!$F$5:$F$25,"Pass") -> 20 | E27: =COUNTIF('1. Health Monitoring'!$F$5:$F$25,"Fail") -> 0 | F27: =COUNTIF('1. Health Monitoring'!$F$5:$F$25,"Partial") -> 0 | G27: =COUNTIF('1. Health Monitoring'!$F$5:$F$25,"Blocked") -> 0 | H27: =COUNTIF('1. Health Monitoring'!$F$5:$F$25,"Not Tested") -> 1 | I27: =IF(C27=0,0,(C27-H27)/C27) -> 0.95238095 | J27: =COUNTIF('1. Health Monitoring'!$I$5:$I$25,"Yes")&" / "&C27 -> 20 / 21
B28: 2. Application Mgmt | C28: =COUNTA('2. Application Mgmt'!$A$5:$A$25) -> 21 | D28: =COUNTIF('2. Application Mgmt'!$F$5:$F$25,"Pass") -> 19 | E28: =COUNTIF('2. Application Mgmt'!$F$5:$F$25,"Fail") -> 0 | F28: =COUNTIF('2. Application Mgmt'!$F$5:$F$25,"Partial") -> 0 | G28: =COUNTIF('2. Application Mgmt'!$F$5:$F$25,"Blocked") -> 0 | H28: =COUNTIF('2. Application Mgmt'!$F$5:$F$25,"Not Tested") -> 2 | I28: =IF(C28=0,0,(C28-H28)/C28) -> 0.9047619 | J28: =COUNTIF('2. Application Mgmt'!$I$5:$I$25,"Yes")&" / "&C28 -> 18 / 21
B29: 3. Customer Support | C29: =COUNTA('3. Customer Support'!$A$5:$A$18) -> 14 | D29: =COUNTIF('3. Customer Support'!$F$5:$F$18,"Pass") -> 14 | E29: =COUNTIF('3. Customer Support'!$F$5:$F$18,"Fail") -> 0 | F29: =COUNTIF('3. Customer Support'!$F$5:$F$18,"Partial") -> 0 | G29: =COUNTIF('3. Customer Support'!$F$5:$F$18,"Blocked") -> 0 | H29: =COUNTIF('3. Customer Support'!$F$5:$F$18,"Not Tested") -> 0 | I29: =IF(C29=0,0,(C29-H29)/C29) -> 1 | J29: =COUNTIF('3. Customer Support'!$I$5:$I$18,"Yes")&" / "&C29 -> 14 / 14
B30: 4. Administrative | C30: =COUNTA('4. Administrative'!$A$5:$A$17) -> 13 | D30: =COUNTIF('4. Administrative'!$F$5:$F$17,"Pass") -> 13 | E30: =COUNTIF('4. Administrative'!$F$5:$F$17,"Fail") -> 0 | F30: =COUNTIF('4. Administrative'!$F$5:$F$17,"Partial") -> 0 | G30: =COUNTIF('4. Administrative'!$F$5:$F$17,"Blocked") -> 0 | H30: =COUNTIF('4. Administrative'!$F$5:$F$17,"Not Tested") -> 0 | I30: =IF(C30=0,0,(C30-H30)/C30) -> 1 | J30: =COUNTIF('4. Administrative'!$I$5:$I$17,"Yes")&" / "&C30 -> 12 / 13
B31: 5. User Management | C31: =COUNTA('5. User Management'!$A$5:$A$21) -> 17 | D31: =COUNTIF('5. User Management'!$F$5:$F$21,"Pass") -> 14 | E31: =COUNTIF('5. User Management'!$F$5:$F$21,"Fail") -> 0 | F31: =COUNTIF('5. User Management'!$F$5:$F$21,"Partial") -> 1 | G31: =COUNTIF('5. User Management'!$F$5:$F$21,"Blocked") -> 0 | H31: =COUNTIF('5. User Management'!$F$5:$F$21,"Not Tested") -> 2 | I31: =IF(C31=0,0,(C31-H31)/C31) -> 0.88235294 | J31: =COUNTIF('5. User Management'!$I$5:$I$21,"Yes")&" / "&C31 -> 10 / 17
B32: 6. ML Estimator API | C32: =COUNTA('6. ML Estimator API'!$A$5:$A$14) -> 10 | D32: =COUNTIF('6. ML Estimator API'!$F$5:$F$14,"Pass") -> 10 | E32: =COUNTIF('6. ML Estimator API'!$F$5:$F$14,"Fail") -> 0 | F32: =COUNTIF('6. ML Estimator API'!$F$5:$F$14,"Partial") -> 0 | G32: =COUNTIF('6. ML Estimator API'!$F$5:$F$14,"Blocked") -> 0 | H32: =COUNTIF('6. ML Estimator API'!$F$5:$F$14,"Not Tested") -> 0 | I32: =IF(C32=0,0,(C32-H32)/C32) -> 1 | J32: =COUNTIF('6. ML Estimator API'!$I$5:$I$14,"Yes")&" / "&C32 -> 10 / 10
B33: 7. NFR & Security | C33: =COUNTA('7. NFR & Security'!$A$5:$A$18) -> 14 | D33: =COUNTIF('7. NFR & Security'!$F$5:$F$18,"Pass") -> 13 | E33: =COUNTIF('7. NFR & Security'!$F$5:$F$18,"Fail") -> 0 | F33: =COUNTIF('7. NFR & Security'!$F$5:$F$18,"Partial") -> 1 | G33: =COUNTIF('7. NFR & Security'!$F$5:$F$18,"Blocked") -> 0 | H33: =COUNTIF('7. NFR & Security'!$F$5:$F$18,"Not Tested") -> 0 | I33: =IF(C33=0,0,(C33-H33)/C33) -> 1 | J33: =COUNTIF('7. NFR & Security'!$I$5:$I$18,"Yes")&" / "&C33 -> 14 / 14
B34: TOTAL | C34: =SUM(C27:C33) -> 110 | D34: =SUM(D27:D33) -> 103 | E34: =SUM(E27:E33) -> 0 | F34: =SUM(F27:F33) -> 2 | G34: =SUM(G27:G33) -> 0 | H34: =SUM(H27:H33) -> 5 | I34: =IF(C34=0,0,(C34-H34)/C34) -> 0.95454545
B37: Sign-off
B39: Student (Ho Kang Kai) | C39: Signature: | G39: Date:
B41: Supervisor | C41: Signature: | G41: Date:

Sheet 1. Health Monitoring
A1: Health Monitoring
A2: Health Monitoring Module (FR1.1 to FR1.17): medical report uploads, reminders, sharing, and admin verification.
A4: Test ID | B4: Req. Ref | C4: Test Item / Feature | D4: Verification Steps | E4: Expected Result | F4: Status | G4: Actual Result / Remarks | H4: Date Tested | I4: Supervisor Verified
A5: HM-01 | B5: FR1.1 | C5: Upload health report (valid file) | D5: Log in as elder; open Health Reports; upload a PDF, JPG and PNG each under 10 MB via file picker and via drag-and-drop; fill report title, type, provider and dates; submit. | E5: All three files upload successfully; report appears in the list with correct metadata and a pending verification status. | F5: Pass | H5: 46213 | I5: Yes
A6: HM-02 | B6: FR1.1 | C6: Upload rejection (invalid file) | D6: Attempt to upload a .docx file, then a PDF larger than 10 MB. | E6: Both uploads are blocked with a plain-language validation message stating the allowed formats (PDF, JPG, PNG) and 10 MB limit; nothing is saved. | F6: Pass | H6: 46213 | I6: Yes
A7: HM-03 | B7: FR1.2 | C7: Report list display | D7: Open the elder's health report list after several uploads. | E7: List shows only the logged-in elder's reports with report name, type, report date, due date and verification status for each entry. | F7: Pass | H7: 46213 | I7: Yes
A8: HM-04 | B8: FR1.3 | C8: Search reports | D8: Enter a partial report name in the search box; repeat with a healthcare provider name; clear the search. | E8: Matching reports are returned for both search modes; clearing restores the full list. | F8: Pass | H8: 46213 | I8: Yes
A9: HM-05 | B9: FR1.4 | C9: Filter reports | D9: Apply filters for report type, a date range, upload status and due status individually and combined; use Clear Filters. | E9: Each filter narrows results correctly; combined filters apply together; Clear Filters restores the full list. | F9: Pass | H9: 46213 | I9: Yes
A10: HM-06 | B10: FR1.5 | C10: Sort reports | D10: Sort by report date, upload date, report type, healthcare provider and due date, toggling ascending and descending for each. | E10: Rows reorder correctly for every field in both directions. | F10: Pass | H10: 46213 | I10: Yes
A11: HM-07 | B11: FR1.6 | C11: Due reminder notification | D11: Create a report reminder with a due date; wait for or trigger the reminder-processor edge function on the due date. | E11: Elder receives an in-system notification (and email where configured) that the health report is due. | F11: Not Tested | G11: Need to test with real email | H11: 46213
A12: HM-08 | B12: FR1.7 | C12: Overdue alert (3 months) | D12: Set a report due date more than three months in the past (test data) and run the reminder process. | E12: An overdue alert is sent to the elder and the report is marked overdue. | F12: Pass | H12: 46213 | I12: Yes
A13: HM-09 | B13: FR1.8 | C13: Share via temporary link | D13: Share a report using the shareable link option (default 7-day expiry); open the /shared-report/:token URL in a private browser window without logging in. | E13: Public page loads the report without authentication; access count increments; expiry date recorded in health_report_shares. | F13: Pass | H13: 46213 | I13: Yes
A14: HM-10 | B14: FR1.8 | C14: Share via email and PDF download | D14: Share a report to a recipient email address; also download the report as a PDF. | E14: Recipient email is sent containing the share link and expiry date; PDF downloads and opens correctly. | F14: Pass | H14: 46213 | I14: Yes
A15: HM-11 | B15: FR1.8 | C15: Expired share link blocked | D15: Set a share record's expires_at to the past (test data) and open its link. | E15: Access is denied with an expiry message; report content is not shown. | F15: Pass | H15: 46213 | I15: Yes
A16: HM-12 | B16: FR1.9 | C16: Document archive persistence | D16: Upload documents, then revisit the account days later while the application remains active. | E16: All submitted health documents remain stored and retrievable for the duration of the active application. | F16: Pass | H16: 46213 | I16: Yes
A17: HM-13 | B17: FR1.10 | C17: Admin views all reports | D17: Log in as admin; open /admin/health-reports. | E17: Reports from all elders are visible, each showing the applicant it belongs to. | F17: Pass | H17: 46213 | I17: Yes
A18: HM-14 | B18: FR1.11-1.13 | C18: Admin search, filter, sort | D18: As admin, search by applicant name, report name and provider name; filter by type, date range, upload status, due status; sort by each supported field asc/desc. | E18: All admin search, filter and sort combinations behave correctly. | F18: Pass | H18: 46213 | I18: Yes
A19: HM-15 | B19: FR1.14 | C19: Admin approves report | D19: As admin, open a submitted report, review the PDF in the viewer, click Approve and confirm. | E19: Report verification status changes to approved and the change is visible to the elder. | F19: Pass | H19: 46213 | I19: Yes
A20: HM-16 | B20: FR1.15 | C20: Admin archives report | D20: As admin, click Archive on a report. | E20: A confirmation prompt appears first; after confirming, the report is archived and removed from the active list. | F20: Pass | H20: 46213 | I20: Yes
A21: HM-17 | B21: FR1.16 | C21: Admin flags report | D21: As admin, flag a report; try to confirm without a reason, then enter a written reason and confirm. | E21: Flagging is blocked until a reason is entered; once flagged, the item is routed to the Customer Support dashboard and the elder is notified. | F21: Pass | H21: 46213 | I21: Yes
A22: HM-18 | B22: FR1.17 | C22: Due-date status badge | D22: As admin, view reports that are up to date, due soon and overdue (test data). | E22: Each report shows the correct badge state: up to date, due soon or overdue. | F22: Pass | H22: 46213 | I22: Yes
A23: HM-19 | B23: - | C23: Reminder maintenance | D23: As elder, create a reminder, edit its date and category, mark it as notified, then delete it. | E23: Create, edit, mark-notified and delete all persist correctly; upcoming and overdue reminder lists refresh. | F23: Pass | H23: 46213 | I23: Yes
... A25: HM-21 | B25: - | C25: Disable and re-enable a reminder | D25: As elder, open Health Reports > Reminders; toggle an active reminder's switch to disable it; expand the 'Disabled reminders' section; toggle it back on. | E25: Disabling removes the reminder from the active list into a collapsible 'Disabled reminders (n)' section; re-toggling it there re-enables it and returns it to the active list; both actions persist and show a confirmation toast. | F25: Pass | H25: 46213 | I25: Yes

Sheet 2. Application Mgmt
A1: Application Mgmt
A2: Application Management Module (FR2.1 to FR2.14): application lifecycle from draft through submission, review, approval and termination.
A4: Test ID | B4: Req. Ref | C4: Test Item / Feature | D4: Verification Steps | E4: Expected Result | F4: Status | G4: Actual Result / Remarks | H4: Date Tested | I4: Supervisor Verified
A5: AM-01 | B5: FR2.1 | C5: Create new application (7-step wizard) | D5: Log in as a new elder; start an application; select the lending organisation; step through Step 1 Personal Information, Step 2 Joint Applicant and Banking, Step 3 Property, Step 4 Nominees, Step 5 Privacy and Declaration, Step 6 Signatures and Documents, Step 7 Review and Submit. | E5: Wizard opens at Step 1 and all seven steps are reachable in order with a visible progress indicator. | F5: Pass | H5: 46213 | I5: Yes
A6: AM-02 | B6: FR2.2 | C6: Draft auto-save and resume | D6: Fill part of Step 2, stop typing for a moment, log out, then log back in and reopen the application. | E6: Form state is auto-saved to Supabase (1-second debounce, localStorage fallback) and the wizard resumes at the saved step with all entered data intact. | F6: Pass | H6: 46213 | I6: Yes
A7: AM-03 | B7: FR2.3 | C7: Automatic eligibility validation | D7: Enter an IC number giving an age below 55, then one above 120, then a valid one (55 to 120). | E7: Underage and overage applicants are blocked with clear messages; valid age passes. Birth date and sex auto-derive from the Malaysian IC (YYMMDD-PB-###G). | F7: Pass | H7: 46213 | I7: Yes
A8: AM-04 | B8: FR2.3 | C8: Per-step field validation | D8: On each step, click Next with required fields empty; enter an invalid IC, phone, postcode, email and account number. | E8: Next is blocked and custom React validation messages identify each invalid field (no browser-native popups); valid input clears the errors. | F8: Pass | H8: 46213 | I8: Yes
A9: AM-05 | B9: FR2.4 | C9: Disqualifying condition alerts | D9: Enter property details that fail scheme criteria (for example non-freehold tenure or unsupported property type) and proceed toward submission. | E9: Clear alerts identify each disqualifying condition before the application can be submitted. | F9: Pass | H9: 46213 | I9: Yes
A10: AM-06 | B10: FR2.5 | C10: Submit completed application | D10: Complete all steps with valid data and signatures, then submit from Step 7. | E10: Nominee and property records are written; a filled PDF is generated from the Application_Form template (signatures embedded on the correct pages); the PDF uploads to the application-forms storage bucket; status changes draft to submitted. | F10: Pass | H10: 46213 | I10: Yes
A11: AM-07 | B11: FR2.6 | C11: Modify before approval | D11: With a submitted (not yet approved) application, edit personal details, property details, uploaded documents and nominee information from the Maintain Application page. | E11: All edits save successfully and are reflected in the application record. | F11: Pass | H11: 46213 | I11: Yes
A12: AM-08 | B12: FR2.7 | C12: Modification locked after approval | D12: After admin approval, attempt to edit the same sections. | E12: All modification actions are disabled or rejected; the application is read-only. | F12: Pass | H12: 46213 | I12: Yes
A13: AM-09 | B13: FR2.8 | C13: Pre-approval cancellation is not offered (design confirmation) | D13: With a submitted or under-review application (not yet approved), open the Maintain Application page and look for any cancel/withdraw action. | E13: No cancel/withdraw action is available before approval. The only cancellation path is 'Terminate Application' on the Maintain Application page, which stays hidden/disabled until the application reaches 'approved' status (see AM-11). | F13: Pass | H13: 46213
A14: AM-10 | B14: FR2.9 | C14: Status and progress visibility | D14: Open the application status page at each lifecycle stage (draft, submitted, underReviewed, approved, terminated). | E14: The current status and a timeline of progress events are always displayed accurately to the elder. | F14: Pass | H14: 46213 | I14: Yes
A15: AM-11 | B15: FR2.10 | C15: Termination request after approval | D15: With an approved application, submit a termination request from the user side. | E15: Request is accepted; status moves approved to underReviewed pending admin decision, and the elder can track it. | F15: Pass | H15: 46213 | I15: Yes
A16: AM-12 | B16: FR2.11 | C16: Nominee property redemption | D16: Using test data for a deceased elder or terminated scheme, submit a property redemption application as the nominee. | E16: Redemption application is created, linked to the original application and visible to the administrator. | F16: Not Tested | H16: 46213
A17: AM-13 | B17: FR2.14 | C17: Status-change notifications | D17: As admin, move an application through submitted, underReviewed, approved (or rejected). | E17: On every status change the elder receives an email or in-system notification stating the new status. | F17: Not Tested | H17: 46213
A18: AM-14 | B18: - | C18: Document upload and replacement in wizard | D18: In Step 6, upload a supporting document, delete it, then upload a replacement. | E18: Upload, delete and replace all work; only the final document remains attached to the application. | F18: Pass | H18: 46213 | I18: Yes
A19: AM-15 | B19: - | C19: Duplicate IC prevention | D19: Enter the applicant's IC again as the joint applicant, then as a nominee; also try a nominee IC already used by another nominee. | E19: Duplicate IC combinations are rejected with a message that the person must not duplicate existing applicant or nominee information. | F19: Pass | H19: 46213 | I19: Yes
A20: AM-16 | B20: - | C20: Generated PDF field mapping | D20: Download the generated application PDF after submission and compare every filled field, checkbox and radio group against the data entered in the wizard. | E20: All fields map correctly; applicant and joint signatures appear on page 4 and the nominee acknowledgement signature on page 6. | F20: Pass | H20: 46213 | I20: Yes
A21: AM-17 | B21: - | C21: Returned-for-correction flow | D21: Have admin return an application with notes; as elder, dismiss the reject reason banner, upload the corrected document and resubmit. | E21: Notes are visible to the elder; corrected resubmission moves the application back into review. | F21: Pass | H21: 46213 | I21: Yes
A22: AM-18 | B22: - | C22: Joint applicant address/marital-status auto-sync | D22: In Step 2 (Joint Applicant and Banking), tick 'Same marital status as applicant' and 'Lives at the same address as applicant'; change the primary applicant's marital status and address. | E22: Once ticked, the joint applicant's marital status, address, postcode and residence phone fields disable and pre-fill from the primary applicant's values, and stay in sync while the checkboxes remain ticked and the primary applicant's details change. | F22: Pass | H22: 46213 | I22: Yes
A23: AM-19 | B23: FR2.4 | C23: Property postcode exclusion validation (free text) | D23: In the Property step, enter a property postcode that is one of the 13 excluded KL postcodes (e.g. 41100); then enter a valid, non-excluded 5-digit postcode. | E23: The excluded postcode is rejected with a message naming it as excluded from eligibility and listing the 13 excluded postcodes; a non-excluded postcode passes. The field is free text, not a restrictive dropdown. | F23: Pass | H23: 46213 | I23: Yes
A24: AM-20 | B24: - | C24: Salutation auto-clears on IC-derived sex mismatch | D24: Select a gendered salutation (e.g. Mr) for the applicant, joint applicant, or a nominee; then edit that person's IC number so the derived sex no longer matches the chosen salutation. | E24: The salutation field clears automatically and an info toast explains it no longer matches the IC-derived gender and must be reselected; gender-neutral salutations and 'Other:' entries are unaffected. | F24: Pass | H24: 46213 | I24: Yes
A25: AM-21 | B25: - | C25: Bank-name dropdown with duplicate detection | D25: In the Banking section, open the 'Name of Bank' dropdown and select a listed bank; then select 'Other' and type the name of a bank already in the list (e.g. 'Maybank'). | E25: The dropdown lists the major Malaysian banks plus 'Other'; choosing 'Other' reveals a free-text field; typing a name matching an already-listed bank is rejected with a message asking the user to pick it from the dropdown instead of typing it. | F25: Pass | H25: 46213 | I25: Yes

Sheet 3. Customer Support
A1: Customer Support
A2: Customer Support Module (FR3.1 to FR3.11): FAQs, tutorials, inquiries, real-time chat and proactive alerts.
A4: Test ID | B4: Req. Ref | C4: Test Item / Feature | D4: Verification Steps | E4: Expected Result | F4: Status | G4: Actual Result / Remarks | H4: Date Tested | I4: Supervisor Verified
A5: CS-01 | B5: FR3.1 | C5: FAQ self-help section | D5: Open the FAQ section as an elder and review entries on application procedure, payout calculation, eligibility and required documents. | E5: FAQ renders correctly and covers the four required topic areas. | F5: Pass | H5: 46213 | I5: Yes
A6: CS-02 | B6: FR3.2 | C6: Step-by-step tutorials | D6: Open the guided tutorial or walkthrough for completing the application form and for uploading health reports. | E6: Tutorials display in order and match the current UI. | F6: Pass | H6: 46213 | I6: Yes
A7: CS-03 | B7: FR3.3 | C7: Submit general inquiry | D7: Submit the contact form empty, then with an invalid and a disposable email, then with valid data. | E7: Invalid submissions are blocked with field-level messages (including temp-email rejection); a valid inquiry is created with status open. | F7: Pass | H7: 46213 | I7: Yes
A8: CS-04 | B8: FR3.4 | C8: Support contact details display | D8: View the support page as an elder. | E8: Current phone number, email address and operating hours are displayed. | F8: Pass | H8: 46213 | I8: Yes
A9: CS-05 | B9: FR3.5 | C9: Critical alerts to elder | D9: Trigger a deadline-approaching alert and a flagged-document alert (test data). | E9: Elder receives an alert notification for both events identifying the deadline or the flagged document. | F9: Pass | H9: 46213 | I9: Yes
A10: CS-06 | B10: FR3.6 | C10: Staff inquiry dashboard | D10: Log in as customer support staff; open the support dashboard. | E10: All inquiries are listed and organised by status (open, in progress, resolved) with working tab or status grouping. | F10: Pass | H10: 46213 | I10: Yes
A11: CS-07 | B11: FR3.7 | C11: Staff reply to inquiry | D11: As staff, open an inquiry and send a reply while the elder has the support page open in another browser. | E11: Reply is stored in support_conversations and appears on the elder's screen in real time without a page refresh. | F11: Pass | H11: 46213 | I11: Yes
A12: CS-08 | B12: - | C12: Two-way real-time chat | D12: Exchange several messages in both directions between elder and staff. | E12: Messages appear live on both sides via Supabase channel subscriptions, in correct order, linked by entity_type and entity_id. | F12: Pass | H12: 46213 | I12: Yes
A13: CS-09 | B13: FR3.8 | C13: Resolve inquiry and lock thread | D13: As staff, mark the inquiry resolved; as elder, attempt to send another message. | E13: Status updates to resolved in real time; the elder's message composer is hidden and sending is blocked in the controller. | F13: Pass | H13: 46213 | I13: Yes
A14: CS-10 | B14: FR3.9 | C14: Proactive notifications | D14: As staff, compose and send a notification to an individual elder, then to a group (for example a deadline reminder). | E14: Both messages are delivered to the intended recipients only. | F14: Pass | H14: 46213 | I14: Yes
A15: CS-11 | B15: FR3.10 | C15: Update public contact info | D15: As staff, edit the displayed phone, email and hours; reload the elder support page. | E15: New contact details persist (settings storage) and are shown to elders. | F15: Pass | H15: 46213 | I15: Yes
A16: CS-12 | B16: FR3.11 | C16: Nominee view and application flagging | D16: As staff, open the nominee details for an elder's application and flag the application with a written reason. | E16: Nominee details display correctly; the flag with its reason is recorded and visible to the administrator. | F16: Pass | H16: 46213 | I16: Yes
... A18: CS-14 | B18: - | C18: Search, filter and sort inquiries | D18: On the staff dashboard, search by keyword, filter by field values and change sort order. | E18: Inquiry list responds correctly to search, filter and sort controls. | F18: Pass | H18: 46213 | I18: Yes

Sheet 4. Administrative
A1: Administrative
A2: Administrative Module (FR4.1 to FR4.7): application review decisions, report generation and oversight tools.
A4: Test ID | B4: Req. Ref | C4: Test Item / Feature | D4: Verification Steps | E4: Expected Result | F4: Status | G4: Actual Result / Remarks | H4: Date Tested | I4: Supervisor Verified
A5: AD-01 | B5: FR4.1 | C5: Application list and detail view | D5: Log in as admin; open the dashboard; select an application to open its full detail page and view supporting documents in the PDF viewer. | E5: All submitted applications are listed with current status; the selected application shows complete details and readable documents. | F5: Pass | H5: 46213 | I5: Yes
A6: AD-02 | B6: FR2.12 | C6: Search, filter and sort applications | D6: Filter the list by status, date and organisation; use the search box; change sort field and order. | E6: List updates correctly for every filter, search and sort combination. | F6: Pass | H6: 46213 | I6: Yes
A7: AD-03 | B7: FR4.2 | C7: Approve application | D7: Open a reviewed application, enter the approved amount, click Approve and confirm in the modal. | E7: Status changes to approved, approved amount is stored, and the elder is notified of the decision. | F7: Pass | H7: 46213 | I7: Yes
A8: AD-04 | B8: FR4.3 | C8: Return with written notes | D8: Return an application with notes specifying required corrections or documents. | E8: Notes are saved and communicated to the applicant; application awaits resubmission. | F8: Pass | H8: 46213 | I8: Yes
A9: AD-05 | B9: FR4.4 | C9: Reject with mandatory reason | D9: Attempt to reject without a reason, then reject with one. | E9: Rejection is blocked until a reason is entered; once rejected, the reason is stored and communicated to the applicant. | F9: Pass | H9: 46213 | I9: Yes
A10: AD-06 | B10: FR4.5 | C10: Generate application analysis report | D10: From an application, generate the analysis report PDF. | E10: PDF is produced containing applicant details, property summary, eligibility check results and current status. | F10: Pass | H10: 46213 | I10: Yes
A11: AD-07 | B11: FR4.6 | C11: Download, print, archive, share report | D11: Use the download, print, archive and share actions on a generated report. | E11: Each action completes: file downloads, print dialog opens with correct layout, archive requires confirmation, share link works. | F11: Pass | H11: 46213 | I11: Yes
A12: AD-08 | B12: FR4.7 | C12: Approve or reject nominee | D12: Approve one nominee and reject another, entering a reason each time. | E12: Decisions and reasons are recorded; nominee status updates are visible to the elder. | F12: Pass | H12: 46213
A13: AD-09 | B13: - | C13: Termination request decision | D13: Approve one termination request and reject another. | E13: Approved request moves the application to terminated (elder is then blocked from /application); rejected request restores approved status. Elder is notified either way. | F13: Pass | H13: 46213 | I13: Yes
A14: AD-10 | B14: - | C14: Flag document during review | D14: While reviewing, flag a specific document; try confirming without a reason first. | E14: Reason is mandatory; flagged document and reason are recorded and routed for elder correction. | F14: Pass | H14: 46213 | I14: Yes
A15: AD-11 | B15: - | C15: Report generator (monthly / analysis) | D15: Open the report generator from the dashboard, choose parameters and confirm generation. | E15: Modal opens, generation completes and the report is available for download. | F15: Pass | H15: 46213 | I15: Yes
A16: AD-12 | B16: - | C16: Admin route protection | D16: While logged in as an elder and as support staff, manually navigate to /admin/dashboard and /admin/review/:id. | E16: Non-admin roles are redirected to their own dashboards; admin pages never render. | F16: Pass | H16: 46213 | I16: Yes
A17: AD-13 | B17: - | C17: Pending-applications quick stats and Days Waiting column | D17: As admin, open the dashboard; click the 'Pending Applications' stat card, then the 'Pending Only' quick-filter button; check the Days Waiting column for a pending application older than 7 days. | E17: Both the stat card and the quick-filter button narrow the list to submitted/underReviewed applications; the Days Waiting column shows days elapsed since submission for pending applications only (blank for others) and is visually flagged once it exceeds 7 days. | F17: Pass | H17: 46213 | I17: Yes

Sheet 5. User Management
A1: User Management
A2: User Management Module (FR5.1 to FR5.9): accounts and access, payouts, disbursements, nominees and property value display.
A4: Test ID | B4: Req. Ref | C4: Test Item / Feature | D4: Verification Steps | E4: Expected Result | F4: Status | G4: Actual Result / Remarks | H4: Date Tested | I4: Supervisor Verified
A5: UM-01 | B5: - | C5: User registration | D5: Register a new account with email and password; check the users table entry; attempt registration with an already-used email. | E5: Account is created with a profile row; duplicate email is rejected with a clear message. | F5: Pass | H5: 46213 | I5: Yes
A6: UM-02 | B6: - | C6: User login and logout | D6: Log in with wrong credentials, then correct ones; log out. | E6: Wrong credentials show an error; successful login lands on the user dashboard; logout clears the session and returns to the login page. | F6: Pass | H6: 46213 | I6: Yes
A7: UM-03 | B7: - | C7: Staff login routing | D7: Log in via the staff login page as an admin account and as a support account. | E7: Admin is routed to /admin/dashboard and support to /support/dashboard, with role resolved from auth metadata or the admins / customer_supports tables. | F7: Pass | H7: 46213 | I7: Yes
A8: UM-04 | B8: - | C8: Status-based route protection | D8: Log in as a user with an incomplete application, then as a user whose application is terminated; try navigating to other routes. | E8: Incomplete user is redirected to /application; terminated user is blocked from /application; role and status survive a page reload (cached in localStorage). | F8: Pass | H8: 46213 | I8: Yes
A9: UM-05 | B9: FR5.1 | C9: Property value estimate on dashboard | D9: Open the user dashboard for an approved application; read the estimated property value; click the re-estimate action. | E9: An estimated value in RM is shown with an indicative-only disclaimer; re-estimation calls the edge function and refreshes the figure. | F9: Pass | H9: 46213
A10: UM-06 | B10: FR5.2 | C10: Payout calculation and toggle | D10: Toggle between monthly payout and lump-sum views on the dashboard. | E10: Estimated payout recalculates from the applicant age, property type, location and verified property value; both views display consistent figures. | F10: Partial | G10: Re-verified 2026-07-10: not outdated - the monthly/lump-sum toggle works and both views show consistent figures. However the calculation only derives from approved_amount/240 (or 70% of property value); applicant age, property type and location are not factored in as FR5.2 describes. | H10: 46213
A11: UM-07 | B11: FR5.3 | C11: Nominee apportioned proceeds | D11: View the apportioned proceeds figure for a nominee using test data at different elapsed times since commencement. | E11: Proceeds payable to the nominee are calculated from time elapsed since the scheme commenced and update with the elapsed period. | F11: Not Tested
A12: UM-08 | B12: FR5.4 | C12: Disbursement history | D12: Open the disbursement history; apply the disbursement filter. | E12: All payouts list amount, date and payment method; filtering narrows the records correctly. | F12: Pass | H12: 46213 | I12: Yes
A13: UM-09 | B13: FR5.5 | C13: Totals and remaining balance | D13: Compare the displayed total disbursed and remaining estimated balance against the individual disbursement records. | E13: Total disbursed equals the sum of records; remaining balance and disbursement percentage are consistent with the approved amount. | F13: Pass | H13: 46213 | I13: Yes
A14: UM-10 | B14: FR5.6 | C14: Nominate a nominee | D14: During the application, add a nominee with name, IC, relationship and contact details; test invalid IC and phone values. | E14: Valid nominee is saved; invalid fields are rejected with clear messages; nominee data auto-populates where supported. | F14: Pass | H14: 46213 | I14: Yes
A15: UM-11 | B15: FR5.7 | C15: Update nominee before approval | D15: Edit nominee details via the edit-nominees route while the application is not yet approved; retry after approval. | E15: Pre-approval edits save; post-approval edits are blocked. | F15: Pass | H15: 46213
A16: UM-12 | B16: - | C16: Save bank details | D16: Enter bank details with an invalid account number, then valid ones, and save. | E16: Invalid account number is rejected; valid details persist and are used for disbursement records. | F16: Pass | H16: 46213 | I16: Yes
A17: UM-13 | B17: FR5.8 | C17: Admin records disbursement | D17: As admin, open /admin/disbursements, select an approved application and create a disbursement with date, amount and method; then edit it. | E17: Only approved applications are selectable; the record saves and updates, and appears in the elder's disbursement history. | F17: Pass | H17: 46213 | I17: Yes
A18: UM-14 | B18: FR5.9 | C18: Verified value update triggers recalculation | D18: As admin, update the verified property value after a formal appraisal; view the elder dashboard afterwards. | E18: New verified value is stored and the elder's displayed payout amounts recalculate from it. | F18: Not Tested
A19: UM-15 | B19: - | C19: Public property calculator page | D19: Open /property-calculator without logging in; submit empty, then with invalid numbers, then valid inputs; use Reset. | E19: Page is publicly accessible; required-field and numeric validation fire; a valid submission returns an estimate; Reset clears the form. | F19: Pass | H19: 46213 | I19: Yes
A20: UM-16 | B20: FR5.8 | C20: Auto-scheduled disbursement review (Confirm / Skip) | D20: As admin, open /admin/disbursements and view the pending auto-scheduled payouts list for approved applications; click Review on a pending slot and Confirm & Record after checking the bank transfer was made; Skip a different slot. | E20: Pending schedule slots (amount = approved_amount / 240, capped at the remaining balance) are listed for admin action. Confirm creates a real transaction record, marks the schedule 'confirmed' and links the transaction_id; Skip marks the schedule 'skipped' with no transaction created; concurrent confirms on the same slot cannot both succeed. | F20: Pass | H20: 46213
A21: UM-17 | B21: - | C21: Pending-disbursement email notification to admins | D21: With one or more schedule rows left pending and un-notified, trigger (or wait for) the daily loan-disbursement-notifier cron job. | E21: Every admin with an email on file receives an HTML email listing applicant/amount/due-date for all pending, not-yet-notified schedule rows, subject '<n> loan disbursement(s) pending confirmation'; notified rows are marked so they aren't re-sent next run. | F21: Pass | H21: 46213

Sheet 6. ML Estimator API
A1: ML Estimator API
A2: Property Value Estimator (FastAPI POST /estimate): XGBoost pipeline with KNN geospatial blending, trained on NAPIC data.
A4: Test ID | B4: Req. Ref | C4: Test Item / Feature | D4: Verification Steps | E4: Expected Result | F4: Status | G4: Actual Result / Remarks | H4: Date Tested | I4: Supervisor Verified
A5: ML-01 | B5: - | C5: API health endpoint | D5: Start the FastAPI service (uvicorn api:app) with the trained model present; call GET /health. | E5: Response is status ok with the resolved model path; with the model file removed, status reports model_not_loaded. | F5: Pass | I5: Yes
A6: ML-02 | B6: - | C6: Valid estimation request | D6: POST /estimate with a complete valid body (property_type, scheme_name, district, mukim, floor_area_sqm, land_area_sqm, tenure, unit_level, txn_year, txn_month). | E6: 200 response containing estimated_price_rm, lower_bound_rm, upper_bound_rm, confidence_band_pct, model_version, currency MYR and the NAPIC disclaimer text. | F6: Pass | I6: Yes
A7: ML-03 | B7: - | C7: Request schema validation | D7: POST /estimate with floor_area_sqm of 0 or negative, txn_month of 13, and a missing required field. | E7: Each invalid request returns HTTP 422 with a field-level validation error; no estimate is produced. | F7: Pass | I7: Yes
A8: ML-04 | B8: - | C8: Model-not-trained handling | D8: Rename or remove the model file and POST /estimate. | E8: API returns HTTP 503 with a clear message that the model is not yet trained; service does not crash. | F8: Pass | I8: Yes
A9: ML-05 | B9: - | C9: Estimate plausibility check | D9: Estimate 3 to 5 properties with known recent NAPIC transaction prices in the same scheme and district. | E9: Each known price falls within or near the returned confidence band; no negative or implausible values (confirms correct inverse of the log-transformed target). | F9: Pass | I9: Yes
A10: ML-06 | B10: - | C10: KNN geospatial blending path | D10: Run an estimate for a property with lat/lon and at least 3 comparables within 10 km, then one without coordinates or comparables. | E10: First case returns the blended output (60 percent XGBoost, 40 percent KNN); second case falls back to the pure XGBoost prediction without error. | F10: Pass | I10: Yes
A11: ML-07 | B11: - | C11: Unseen category handling | D11: POST /estimate with a scheme_name and mukim that do not exist in the training data. | E11: Target encoding falls back gracefully (global or district-level statistics); a reasonable estimate is still returned without a crash. | F11: Pass | I11: Yes
A12: ML-08 | B12: - | C12: Leakage and feature checks | D12: Inspect the inference feature set used by the pipeline for a sample request. | E12: price_per_sqm is excluded at inference; engineered features (area_ratio, is_freehold, is_high_rise, cyclical month encoding, district-period rolling median) are computed as designed. | F12: Pass | I12: Yes
A13: ML-09 | B13: - | C13: Training reproducibility and versioning | D13: Re-run the training pipeline on the NAPIC dataset. | E13: Time-based train/test split is applied; MAPE and R2 for XGBoost and the Random Forest comparison are logged; a versioned model file (xgb_erumah_<version>.pkl) is exported and picked up by the API model_version string. | F13: Pass | I13: Yes
A14: ML-10 | B14: - | C14: Frontend integration and error handling | D14: Use the property calculator UI with the API running, then with the API stopped. | E14: With the API up, the RM estimate, bounds and disclaimer render in the UI (CORS permits the request); with the API down, a friendly error message is shown instead of a blank or broken page. | F14: Pass | I14: Yes

Sheet 7. NFR & Security
A1: NFR & Security
A2: Non-functional requirements (NFR1 Performance, NFR2 Usability, NFR3 Security) and cross-cutting verification.
A4: Test ID | B4: Req. Ref | C4: Test Item / Feature | D4: Verification Steps | E4: Expected Result | F4: Status | G4: Actual Result / Remarks | H4: Date Tested | I4: Supervisor Verified
A5: NF-01 | B5: NFR1.1 | C5: Page load performance | D5: Measure load time of the dashboard and health report list with browser dev tools under normal conditions (3 runs each). | E5: Every measured page fully loads within 3 seconds. | F5: Pass | H5: 13/07/2026 | I5: Yes
A6: NF-02 | B6: NFR1.2 | C6: Upload performance | D6: Upload a health report file close to 10 MB on a standard broadband connection and time it. | E6: Upload completes within 5 seconds. | F6: Pass | H6: 13/07/2026 | I6: Yes
A7: NF-03 | B7: NFR1.3 | C7: Search, filter and sort responsiveness | D7: Time representative search, filter and sort operations on the health report and application lists. | E7: Results return within 2 seconds of the request. | F7: Pass | H7: 13/07/2026 | I7: Yes
A8: NF-04 | B8: NFR1.4 | C8: Report generation time | D8: Time the generation of an application analysis PDF. | E8: PDF is generated and available for download within 10 seconds. | F8: Pass | H8: 13/07/2026 | I8: Yes
A9: NF-05 | B9: NFR2.1 | C9: Typography standards | D9: Inspect rendered pages with dev tools across the five modules. | E9: Body text is at least 14pt, headings at least 18pt, and the primary typeface is Inter. | F9: Pass | H9: 13/07/2026 | I9: Yes
A10: NF-06 | B10: NFR2.2 | C10: Colour and contrast compliance | D10: Run a WCAG contrast checker on key screens; verify palette usage. | E10: Colour combinations meet WCAG 2.1 AA contrast; the palette of #A8202D, #1F3864 and #FFFFFF is applied consistently. | F10: Pass | H10: 13/07/2026 | I10: Yes
A11: NF-07 | B11: NFR2.3 | C11: Plain-language validation messages | D11: Review validation messages triggered across the application, enquiry and health report forms. | E11: Every message is plain language, names the field in error and states the corrective action. | F11: Pass | H11: 13/07/2026 | I11: Yes
A12: NF-08 | B12: NFR3.1 | C12: Authentication and session expiry | D12: Access module URLs while logged out; then log in and stay idle for 30 minutes before acting again. | E12: Unauthenticated access is redirected to login for every module; after 30 minutes of inactivity the session expires and re-login is required. | F12: Pass | H12: 13/07/2026 | I12: Yes
A13: NF-09 | B13: NFR3.2 | C13: Transport encryption | D13: Inspect the deployed site's connections in browser dev tools (security tab). | E13: All client-server traffic uses HTTPS with TLS 1.2 or higher; no mixed content. | F13: Pass | H13: 13/07/2026 | I13: Yes
A14: NF-10 | B14: NFR3.3 | C14: Role-based access control | D14: As an elder, attempt admin and support URLs; as support, attempt admin URLs and disbursement modification. | E14: Each role can only reach its own module routes; elders access only their own records; support cannot modify disbursement records. | F14: Pass | H14: 13/07/2026 | I14: Yes
A15: NF-11 | B15: NFR3.3 | C15: Row-level security (data isolation) | D15: Using the browser session of elder A (or the Supabase client with A's token), query health_reports and applications belonging to elder B. | E15: RLS policies return no rows or deny the request; one elder can never read another elder's records. | F15: Pass | H15: 13/07/2026 | I15: Yes
A16: NF-12 | B16: NFR3.4 | C16: Audit logging | D16: Perform a document upload, an application status change, an admin approval and a login; inspect the log records. | E16: Each event is logged with the user ID, action type and timestamp. | F16: Pass | H16: 13/07/2026 | I16: Yes
... A18: NF-14 | B18: - | C18: Cross-browser verification | D18: Smoke-test login, application wizard, health upload and support chat on Chrome, Edge and Firefox. | E18: Core flows work identically on all three browsers with no console errors. | F18: Pass | H18: 13/07/2026 | I18: Yes
